tihmdri/__init__.py
tihmdri/clean.py
tihmdri/plots.py
tihmdri/sandbox.py
tihmdri/utils.py
tihmDri-0.1.7.dist-info/METADATA
tihmDri-0.1.7.dist-info/WHEEL
tihmDri-0.1.7.dist-info/top_level.txt
tihmDri-0.1.7.dist-info/RECORD
