Metadata-Version: 2.1
Name: tihmDri
Version: 0.1.7
Summary: A package to process tihm iot datasets
Home-page: https://github.com/esoreq/tihmdri.git
Author: Eyal Soreq
Author-email: eyalsoreq@gmail.com
License: UNKNOWN
Platform: UNKNOWN
Classifier: Programming Language :: Python :: 3.9
Classifier: License :: OSI Approved :: GNU General Public License v3 (GPLv3)
Requires-Dist: numpy (>=1.19)
Requires-Dist: pandas (>=1.1)
